xchainpy2_thorchain_amm/__init__.py
xchainpy2_thorchain_amm/amm.py
xchainpy2_thorchain_amm/consts.py
xchainpy2_thorchain_amm/evm_helper.py
xchainpy2_thorchain_amm/models.py
xchainpy2_thorchain_amm/utils.py
xchainpy2_thorchain_amm/tests/__init__.py
xchainpy2_thorchain_amm/tests/test_name.py
xchainpy2_thorchain_amm-0.0.34.dist-info/licenses/LICENSE
xchainpy2_thorchain_amm-0.0.34.dist-info/METADATA
xchainpy2_thorchain_amm-0.0.34.dist-info/WHEEL
xchainpy2_thorchain_amm-0.0.34.dist-info/top_level.txt
xchainpy2_thorchain_amm-0.0.34.dist-info/RECORD
